{
    "productList": [
        {
            "id": 1,
            "name": "ไข่ตุ๋นหมูสับ",
            "description": "สำหรับเมนูนี้เราสามารถทำได้โดยใช้ไมโครเวฟเท่านั้น เอาใจเด็กหอหรือคนที่ต้องการความรวดเร็ว ไม่ใช่แค่นั้นนะ ไข่ตุ๋นยังเป็นเมนูที่ติดอันดับต้นๆ ของคนรักสุขภาพด้วย",
            "price": 120,
            "cost": 100,
            "date": "28/4/2021",
            "img": "https://static.wixstatic.com/media/b4c676_ac5bf0938f3048af80f31490ed9b70a1~mv2.jpg/v1/fill/w_740,h_443,al_c,q_90,usm_0.66_1.00_0.01/b4c676_ac5bf0938f3048af80f31490ed9b70a1~mv2.webp",
            "brand": "Main Menu",
            "size":  "M"
        },
        {
            "id": 2,
            "name": "ต้มยำกุ้ง",
            "description": "าเป็นซุปแบบไทยที่เป็นที่รู้จักมากที่สุดและเป็นที่นิยมมากที่สุดไม่เฉพาะแต่ในเมืองไทยเท่านั้น แต่ยังเป็นที่นิยมในร้านอาหาร (และครัวไทย) อื่นๆทั่วโลก ต้มยำเป็นซุปรสเปรี้ยวปรุงด้วยเครื่องเทศของไทยที่เป็นที่นิยมหลากหลายชนิด: ทั้งตะไคร้กลิ่นหอมหวน แง่งข่าสด และใบมะกรูด",
            "price": 200,
            "cost": 150,
            "date": "28/4/2021",
            "img": "http://3.bp.blogspot.com/-X9dP-MSMlIw/VJBRjKAUk7I/AAAAAAAAAHU/WhedLBbA4_M/s1600/m3_01.jpg",
            "brand": "Main Menu",
            "size":  "M"
        }
    ]
}